rocketchat_API/__init__.py
rocketchat_API/rocketchat.py
rocketchat_API/APIExceptions/RocketExceptions.py
rocketchat_API/APIExceptions/__init__.py
rocketchat_API/APISections/__init__.py
rocketchat_API/APISections/assets.py
rocketchat_API/APISections/banners.py
rocketchat_API/APISections/base.py
rocketchat_API/APISections/channels.py
rocketchat_API/APISections/chat.py
rocketchat_API/APISections/dm.py
rocketchat_API/APISections/groups.py
rocketchat_API/APISections/integrations.py
rocketchat_API/APISections/invites.py
rocketchat_API/APISections/licenses.py
rocketchat_API/APISections/livechat.py
rocketchat_API/APISections/miscellaneous.py
rocketchat_API/APISections/permissions.py
rocketchat_API/APISections/roles.py
rocketchat_API/APISections/rooms.py
rocketchat_API/APISections/settings.py
rocketchat_API/APISections/statistics.py
rocketchat_API/APISections/subscriptions.py
rocketchat_API/APISections/teams.py
rocketchat_API/APISections/users.py
rocketchat_api-3.1.0.dist-info/licenses/LICENSE.txt
rocketchat_api-3.1.0.dist-info/METADATA
rocketchat_api-3.1.0.dist-info/WHEEL
rocketchat_api-3.1.0.dist-info/top_level.txt
rocketchat_api-3.1.0.dist-info/RECORD
