Metadata-Version: 2.4
Name: rocketchat_API
Version: 3.1.0
Summary: Python API wrapper for Rocket.Chat
Author-email: "Jorge Alberto Díaz Orozco (Akiel)" <diazorozcoj@gmail.com>
Maintainer-email: "Jorge Alberto Díaz Orozco (Akiel)" <diazorozcoj@gmail.com>
License-Expression: MIT
Project-URL: Homepage, https://github.com/jadolg/rocketchat_API
Project-URL: Issues, https://github.com/jadolg/rocketchat_API/issues
Keywords: rocketchat,api,wrapper,rest
License-File: LICENSE.txt
Requires-Dist: requests
Requires-Dist: packaging
Provides-Extra: test
Requires-Dist: black; extra == "test"
Requires-Dist: pytest; extra == "test"
Requires-Dist: pytest-cov; extra == "test"
Requires-Dist: requests; extra == "test"
Requires-Dist: semver; extra == "test"
Dynamic: license-file
